tests/__init__.py
tests/test_urls.py
urltitle/__init__.py
urltitle/urltitle.py
urltitle/config/__init__.py
urltitle/config/overrides.py
urltitle/util/__init__.py
urltitle/util/humanize.py
urltitle/util/json.py
urltitle/util/math.py
urltitle/util/pikepdf.py
urltitle/util/urllib.py
urltitle-0.3.8.dist-info/LICENSE
urltitle-0.3.8.dist-info/METADATA
urltitle-0.3.8.dist-info/WHEEL
urltitle-0.3.8.dist-info/top_level.txt
urltitle-0.3.8.dist-info/RECORD
