Metadata-Version: 2.1
Name: urltitle
Version: 0.3.8
Summary: Get page title for URL
Home-page: https://github.com/impredicative/urltitle/
Author: Ouroboros Chrysopoeia
Author-email: impredicative@users.noreply.github.com
License: UNKNOWN
Keywords: url title
Platform: UNKNOWN
Classifier: Programming Language :: Python :: 3.7
Classifier: License :: OSI Approved :: GNU Affero General Public License v3
Classifier: Topic :: Internet :: WWW/HTTP
Classifier: Topic :: Software Development :: Libraries :: Python Modules
Requires-Python: >=3.7
License-File: LICENSE
Requires-Dist: beautifulsoup4 (>=4.9.1)
Requires-Dist: cachetools (>=4.1.1)
Requires-Dist: humanize (>=2.6.0)
Requires-Dist: pikepdf (>=1.18.0)
